{
  "name" : "Tales of Elleria Relics",
  "website" : "https://www.talesofelleria.com/",
  "description" : "Tales of Elleria is an immersive three-dimensional role-playing GameFi project built on Arbitrum One. Summon heroes, take on assignments, go on quests and epic adventures to battle dangerous monsters and earn tremendous rewards.",
  "explorer" : "https://arbiscan.io/token/0x381227255eF6c5d85966b78d13e4B4a4c8719b5E",
  "type" : "ARC1155",
  "symbol" : null,
  "decimals" : "1",
  "status" : "active",
  "id" : "0x381227255eF6c5d85966b78d13e4B4a4c8719b5E",
  "tags" : null,
  "links" : [ {
    "name" : "discord",
    "url" : "https://discord.gg/f5q9KM4c"
  } ]
}